zensectfpy/__init__.py
zensectfpy/rickroll.py
zensectfpy/top_secret_wisefox_64.py
zensectfpy-0.0.2.dist-info/LICENSE
zensectfpy-0.0.2.dist-info/METADATA
zensectfpy-0.0.2.dist-info/WHEEL
zensectfpy-0.0.2.dist-info/top_level.txt
zensectfpy-0.0.2.dist-info/RECORD
